stClinic/Module.py
stClinic/Utilities.py
stClinic/__init__.py
stClinic/gat_conv.py
stClinic/mnn_utils.py
stClinic-0.0.10.dist-info/LICENSE
stClinic-0.0.10.dist-info/METADATA
stClinic-0.0.10.dist-info/WHEEL
stClinic-0.0.10.dist-info/top_level.txt
stClinic-0.0.10.dist-info/RECORD
