Metadata-Version: 2.1
Name: stClinic
Version: 0.0.10
Summary: stClinic for dissecting clinically relevant niches by integrating spatial multi-slice multi-omics data
Home-page: https://github.com/cmzuo11/stClinic
Author: cmzuo
Author-email: cmzuo13@163.com
License: MIT License
Keywords: TME
Platform: any
License-File: LICENSE
Requires-Dist: anndata==0.9.2
Requires-Dist: numpy==1.22.3
Requires-Dist: pandas==2.0.3
Requires-Dist: scipy==1.10.1
Requires-Dist: matplotlib==3.7.2
Requires-Dist: scanpy==1.9.3
Requires-Dist: umap-learn==0.5.3
Requires-Dist: louvain==0.8.1
Requires-Dist: h5py==3.9.0
Requires-Dist: torch==2.4.0
Requires-Dist: faiss-gpu
Requires-Dist: torchaudio==2.4.0
Requires-Dist: torchvision==0.19.0
Requires-Dist: tqdm==4.65.0
Requires-Dist: hnswlib==0.5.1
Requires-Dist: rpy2==3.5.1
Requires-Dist: scikit-learn==1.3.0
Requires-Dist: scikit-misc==0.2.0
Requires-Dist: seaborn==0.11.2
Requires-Dist: lifelines==0.27.8
Requires-Dist: networkx==3.1
Requires-Dist: igraph==0.10.8
Requires-Dist: python-igraph==0.10.8
Requires-Dist: torch-sparse==0.6.18
Requires-Dist: torch-scatter==2.1.2
